schema_validator/__init__.py
schema_validator/command.py
schema_validator/constants.py
schema_validator/core.py
schema_validator/flask/__init__.py
schema_validator/flask/api.py
schema_validator/flask/validation.py
schema_validator/quart/__init__.py
schema_validator/quart/api.py
schema_validator/quart/validation.py
schema_validator/types.py
schema_validator/utils.py
schema_validator-0.2.5.dist-info/LICENSE
schema_validator-0.2.5.dist-info/WHEEL
schema_validator-0.2.5.dist-info/METADATA
schema_validator-0.2.5.dist-info/RECORD
