Metadata-Version: 2.1
Name: schema-validator
Version: 0.2.5
Summary: A flask/quart extension to provide schema validation with pydantic.
Home-page: https://github.com/huangxiaohen2738/schema-validator
License: MIT
Author: hs
Author-email: huangxiaohen2738@gmail.com
Requires-Python: >=3.7
Classifier: Environment :: Web Environment
Classifier: Intended Audience :: Developers
Classifier: License :: OSI Approved :: MIT License
Classifier: Programming Language :: Python
Classifier: Programming Language :: Python :: 3
Classifier: Programming Language :: Python :: 3.6
Classifier: Programming Language :: Python :: 3.7
Classifier: Programming Language :: Python :: 3.8
Classifier: Programming Language :: Python :: 3.9
Provides-Extra: flask
Provides-Extra: quart
Requires-Dist: pydantic (>=1.8)
Requires-Dist: pyhumps
Project-URL: Repository, https://github.com/huangxiaohen2738/schema-validator
